{
  "schema_version": 1,
  "event_type": "state-patched",
  "feature_registry_key": "phase1/governed-state-writer-serialization",
  "run_id": "run-d6865164-1f94-4e4f-b88a-3d0cdd5449e7",
  "run_mode": "normal",
  "attempt_id": "attempt-001",
  "occurred_at": "2026-04-09T08:13:28.101Z",
  "payload": {
    "changed_fields": [
      "implementor_reasoning_effort",
      "feature_status",
      "local_target_sync_status",
      "last_completed_step",
      "last_commit_sha",
      "active_run_status",
      "human_verification_approved_at",
      "human_verification_approved_commit_sha"
    ]
  },
  "event_id": "event-84a64eb1-0168-4c90-a244-73330f5c0454"
}
